st_tools/__init__.py
st_tools/_version.py
st_tools/session_state_manager.py
st_tools-1.0.1.dist-info/LICENSE
st_tools-1.0.1.dist-info/METADATA
st_tools-1.0.1.dist-info/WHEEL
st_tools-1.0.1.dist-info/top_level.txt
st_tools-1.0.1.dist-info/RECORD
