Metadata-Version: 2.1
Name: st_tools
Version: 1.0.1
Summary: Tools for streamlit
Home-page: https://github.com/dsblank/st_tools
Author: st_tools Development Team
License: MIT License
Keywords: streamlit
Platform: Linux
Platform: Mac OS X
Platform: Windows
Classifier: License :: OSI Approved :: MIT License
Classifier: Programming Language :: Python
Classifier: Programming Language :: Python :: 3
Classifier: Programming Language :: Python :: 3.7
Classifier: Programming Language :: Python :: 3.8
Classifier: Programming Language :: Python :: 3.9
Classifier: Programming Language :: Python :: 3.10
Requires-Python: >=3.7
License-File: LICENSE
